ultranlp/__init__.py
ultranlp/core.py
ultranlp/utils.py
ultranlp-1.0.6.dist-info/licenses/LICENSE
ultranlp-1.0.6.dist-info/METADATA
ultranlp-1.0.6.dist-info/WHEEL
ultranlp-1.0.6.dist-info/top_level.txt
ultranlp-1.0.6.dist-info/RECORD
