Metadata-Version: 2.4
Name: ultranlp
Version: 1.0.6
Summary: Ultra-fast, comprehensive NLP preprocessing library with advanced tokenization
Home-page: https://github.com/dushyantzz/UltraNLP
Author: Dushyant
Author-email: dushyantkv508@gmail.com
Keywords: nlp,text-processing,tokenization,preprocessing,machine-learning,natural-language-processing,fast,advanced,social-media,currency,email
Classifier: Development Status :: 5 - Production/Stable
Classifier: Intended Audience :: Developers
Classifier: License :: OSI Approved :: MIT License
Classifier: Programming Language :: Python :: 3.8
Classifier: Programming Language :: Python :: 3.9
Classifier: Programming Language :: Python :: 3.10
Classifier: Programming Language :: Python :: 3.11
Classifier: Programming Language :: Python :: 3.12
Classifier: Topic :: Text Processing :: Linguistic
Classifier: Topic :: Scientific/Engineering :: Artificial Intelligence
Requires-Python: >=3.8
License-File: LICENSE
Requires-Dist: beautifulsoup4>=4.9.0
Provides-Extra: dev
Requires-Dist: pytest>=6.0; extra == "dev"
Requires-Dist: black; extra == "dev"
Requires-Dist: flake8; extra == "dev"
Requires-Dist: mypy; extra == "dev"
Provides-Extra: benchmark
Requires-Dist: matplotlib; extra == "benchmark"
Requires-Dist: pandas; extra == "benchmark"
Requires-Dist: seaborn; extra == "benchmark"
Dynamic: author
Dynamic: author-email
Dynamic: classifier
Dynamic: description
Dynamic: description-content-type
Dynamic: home-page
Dynamic: keywords
Dynamic: license-file
Dynamic: provides-extra
Dynamic: requires-dist
Dynamic: requires-python
Dynamic: summary
